trytond/modules/health_webdav3_server/README.rst
trytond/modules/health_webdav3_server/__init__.py
trytond/modules/health_webdav3_server/bin/gnuhealth-webdav-server
trytond/modules/health_webdav3_server/data/messages/messages.xml
trytond/modules/health_webdav3_server/exceptions.py
trytond/modules/health_webdav3_server/locale/ar.po
trytond/modules/health_webdav3_server/locale/bg.po
trytond/modules/health_webdav3_server/locale/cs.po
trytond/modules/health_webdav3_server/locale/de.po
trytond/modules/health_webdav3_server/locale/el.po
trytond/modules/health_webdav3_server/locale/eo.po
trytond/modules/health_webdav3_server/locale/es.po
trytond/modules/health_webdav3_server/locale/fr.po
trytond/modules/health_webdav3_server/locale/health_webdav3_server.pot
trytond/modules/health_webdav3_server/locale/it_IT.po
trytond/modules/health_webdav3_server/locale/ja_JP.po
trytond/modules/health_webdav3_server/locale/ka.po
trytond/modules/health_webdav3_server/locale/lo.po
trytond/modules/health_webdav3_server/locale/pt_BR.po
trytond/modules/health_webdav3_server/locale/sv.po
trytond/modules/health_webdav3_server/locale/tr.po
trytond/modules/health_webdav3_server/locale/uk.po
trytond/modules/health_webdav3_server/locale/zh_CN.po
trytond/modules/health_webdav3_server/protocol.py
trytond/modules/health_webdav3_server/pyproject.toml
trytond/modules/health_webdav3_server/server.py
trytond/modules/health_webdav3_server/tests/__init__.py
trytond/modules/health_webdav3_server/tests/test_webdav.py
trytond/modules/health_webdav3_server/tryton.cfg
trytond/modules/health_webdav3_server/view/attachment_form.xml
trytond/modules/health_webdav3_server/view/collection_form.xml
trytond/modules/health_webdav3_server/view/collection_list.xml
trytond/modules/health_webdav3_server/view/collection_tree.xml
trytond/modules/health_webdav3_server/view/share_form.xml
trytond/modules/health_webdav3_server/view/share_list.xml
trytond/modules/health_webdav3_server/webdav.py
gnuhealth_webdav3_server-5.0.2.dist-info/METADATA
gnuhealth_webdav3_server-5.0.2.dist-info/WHEEL
gnuhealth_webdav3_server-5.0.2.dist-info/RECORD
